{
  "products": [
    {
      "id": "1",
      "name": "Laptop HP Pavilion",
      "type": "Informatique",
      "barcode": "1234567890123",
      "price": 1200,
      "solde": 1100,
      "supplier": "HP",
      "image": "https://mediazone.ma/uploads/images/products/16412/landing-page/assets/images/swiper-1.png",
      "stocks": [
        {
          "id": 1999,
          "name": "Gueliz B2",
          "quantity": 16,
          "localisation": {
            "city": "Marrakesh",
            "latitude": 31.628674,
            "longitude": -7.992047
          }
        },
        {
          "id": 2991,
          "name": "Lazari H2",
          "quantity": 9,
          "localisation": {
            "city": "Oujda",
            "latitude": 34.689404,
            "longitude": -1.912823
          }
        }
      ],
      "editedBy": [
        {
          "warehousemanId": 1333,
          "at": "2025-02-02"
        }
      ]
    },
    {
      "id": "2",
      "name": "Clavier Mécanique Logitech",
      "type": "Accessoires",
      "barcode": "9876543210987",
      "price": 100,
      "supplier": "Logitech",
      "image": "https://in-media.apjonlinecdn.com/catalog/product/cache/b3b166914d87ce343d4dc5ec5117b502/8/a/8aa01aa.png",
      "stocks": [
        {
          "id": 1999,
          "name": "Gueliz B2",
          "quantity": 19,
          "localisation": {
            "city": "Marrakesh",
            "latitude": 31.628674,
            "longitude": -7.992047
          }
        },
        {
          "id": 2991,
          "name": "Lazari H2",
          "quantity": 8,
          "localisation": {
            "city": "Oujda",
            "latitude": 34.689404,
            "longitude": -1.912823
          }
        }
      ],
      "editedBy": [
        {
          "warehousemanId": 1444,
          "at": "2025-02-02"
        }
      ]
    },
    {
      "id": "1d0e",
      "name": "New Product",
      "type": "Type A",
      "barcode": "123456",
      "price": 100,
      "supplier": "Supplier A",
      "image": "image_url",
      "stocks": []
    },
    {
      "id": "5063",
      "name": "New Product",
      "type": "Type A",
      "barcode": "123456",
      "price": 100,
      "supplier": "Supplier A",
      "image": "image_url",
      "stocks": []
    },
    {
      "id": "8b86",
      "name": "New Product",
      "type": "Type A",
      "barcode": "123456",
      "price": 100,
      "supplier": "Supplier A",
      "image": "image_url",
      "stocks": []
    },
    {
      "id": "6464",
      "name": "New Product",
      "type": "Type A",
      "barcode": "123456",
      "price": 100,
      "supplier": "Supplier A",
      "image": "image_url",
      "stocks": []
    },
    {
      "id": "57d2",
      "name": "New Product",
      "type": "Type A",
      "barcode": "123456",
      "price": 100,
      "supplier": "Supplier A",
      "image": "image_url",
      "stocks": []
    },
    {
      "id": "a12e",
      "name": "New Product",
      "type": "Type A",
      "barcode": "123456",
      "price": 100,
      "supplier": "Supplier A",
      "image": "image_url",
      "stocks": []
    },
    {
      "id": "0802",
      "name": "New Product",
      "type": "Type A",
      "barcode": "123456",
      "price": 100,
      "supplier": "Supplier A",
      "image": "image_url",
      "stocks": []
    },
    {
      "id": "0163",
      "name": "New Product",
      "type": "Type A",
      "barcode": "123456",
      "price": 100,
      "supplier": "Supplier A",
      "image": "image_url",
      "stocks": []
    },
    {
      "id": "47c7",
      "name": "New Product",
      "type": "Type A",
      "barcode": "123456",
      "price": 100,
      "supplier": "Supplier A",
      "image": "image_url",
      "stocks": []
    },
    {
      "id": "942a",
      "name": "New Product",
      "type": "Type A",
      "barcode": "123456",
      "price": 100,
      "supplier": "Supplier A",
      "image": "image_url",
      "stocks": []
    },
    {
      "id": "20fd",
      "name": "New Product",
      "type": "Type A",
      "barcode": "123456",
      "price": 100,
      "supplier": "Supplier A",
      "image": "image_url",
      "stocks": []
    }
  ],
  "warehousemans": [
    {
      "id": "1333",
      "name": "Amine Boutaleb",
      "dob": "1988-05-02",
      "city": "Oujda",
      "secretKey": "0",
      "warehouseId": 1999
    },
    {
      "id": "1444",
      "name": "Karim El Mansouri",
      "dob": "1990-09-15",
      "city": "Marrakesh",
      "secretKey": "RK189987A",
      "warehouseId": 2991
    }
  ],
  "statistics": {
    "totalProducts": 3,
    "outOfStock": 1,
    "totalStockValue": 70,
    "mostAddedProducts": [],
    "mostRemovedProducts": []
  }
}